setup.py
pytest123/__init__.py
pytest123.egg-info/PKG-INFO
pytest123.egg-info/SOURCES.txt
pytest123.egg-info/dependency_links.txt
pytest123.egg-info/not-zip-safe
pytest123.egg-info/top_level.txt