Metadata-Version: 1.0
Name: pytest123
Version: 0.0.1
Summary: Test Library
Home-page: UNKNOWN
Author: rboyapat
Author-email: rboyapat@gmail.com
License: MIT
Platform: UNKNOWN
